spearmint/__init__.py
spearmint/_version.py
spearmint/config.py
spearmint/dataset.py
spearmint/distributions.py
spearmint/experiment.py
spearmint/hypothesis_test.py
spearmint/mixin.py
spearmint/stats.py
spearmint/table.py
spearmint/typing.py
spearmint/utils.py
spearmint/vis.py
spearmint/inference/__init__.py
spearmint/inference/inference_base.py
spearmint/inference/bayesian/__init__.py
spearmint/inference/bayesian/bayesian_inference.py
spearmint/inference/bayesian/models/__init__.py
spearmint/inference/bayesian/models/analytic_base.py
spearmint/inference/bayesian/models/binary.py
spearmint/inference/bayesian/models/continuous.py
spearmint/inference/bayesian/models/counts.py
spearmint/inference/frequentist/__init__.py
spearmint/inference/frequentist/bootstrap_delta.py
spearmint/inference/frequentist/frequentist_inference.py
spearmint/inference/frequentist/means_delta.py
spearmint/inference/frequentist/proportions_delta.py
spearmint/inference/frequentist/rates_ratio.py
spearmint-0.0.2.dist-info/LICENSE
spearmint-0.0.2.dist-info/METADATA
spearmint-0.0.2.dist-info/WHEEL
spearmint-0.0.2.dist-info/top_level.txt
spearmint-0.0.2.dist-info/zip-safe
spearmint-0.0.2.dist-info/RECORD
