Metadata-Version: 2.1
Name: spearmint
Version: 0.0.2
Summary: Refreshing hypothesis testing in python!
Author-email: Dustin Stansbury <dustin.stansbury@gmail.com>
Maintainer-email: Dustin Stansbury <dustin.stansbury@gmail.com>
License: Copyright (c) 2024, Dustin E. Stansbury
Project-URL: Homepage, https://github.com/dustinstansbury/spearmint
Project-URL: Documentation, https://github.com/dustinstansbury/spearmint
Project-URL: Repository, https://github.com/dustinstansbury/spearmint.git
Project-URL: Bug Tracker, https://github.com/dustinstansbury/spearmint/issues
Project-URL: Changelog, https://github.com/dustinstansbury/spearmint/blob/main/CHANGELOG.md
Keywords: data science,hypothesis testing,AB testing,statistics,bayesian inference,bootstrap statistics
Classifier: Programming Language :: Python
Classifier: Development Status :: 4 - Beta
Classifier: Framework :: Jupyter :: JupyterLab
Classifier: Topic :: Scientific/Engineering
Requires-Python: >=3.10
License-File: LICENSE
Requires-Dist: numpy >=1.25.2
Requires-Dist: scipy >=1.11.2
Requires-Dist: statsmodels >=0.14.0
Requires-Dist: pandas >=2.1.1
Requires-Dist: pymc >=5.8.0
Requires-Dist: holoviews >=1.18.0
Requires-Dist: matplotlib >=3.8.0
Requires-Dist: rich
Provides-Extra: notebook
Requires-Dist: jupyterlab >=4.0.6 ; extra == 'notebook'
Provides-Extra: test
Requires-Dist: ruff ; extra == 'test'
Requires-Dist: mypy ; extra == 'test'
Requires-Dist: pytest ; extra == 'test'
Requires-Dist: pytest-coverage ; extra == 'test'
